MANIFEST.in
README.txt
setup.cfg
setup.py
docs/HISTORY.txt
docs/INSTALL.txt
docs/LICENSE.txt
pegasus/__init__.py
pegasus.theme.egg-info/PKG-INFO
pegasus.theme.egg-info/SOURCES.txt
pegasus.theme.egg-info/dependency_links.txt
pegasus.theme.egg-info/entry_points.txt
pegasus.theme.egg-info/namespace_packages.txt
pegasus.theme.egg-info/not-zip-safe
pegasus.theme.egg-info/paster_plugins.txt
pegasus.theme.egg-info/requires.txt
pegasus.theme.egg-info/top_level.txt
pegasus/theme/__init__.py
pegasus/theme/configure.zcml
pegasus/theme/profiles.zcml
pegasus/theme/setuphandlers.py
pegasus/theme/skins.zcml
pegasus/theme/tests.py
pegasus/theme/version.txt
pegasus/theme/browser/__init__.py
pegasus/theme/browser/configure.zcml
pegasus/theme/browser/interfaces.py
pegasus/theme/browser/viewlet.pt
pegasus/theme/browser/viewlets.py
pegasus/theme/browser/images/README.txt
pegasus/theme/browser/images/ajax-loader.gif
pegasus/theme/browser/images/ajax-loader2.gif
pegasus/theme/browser/images/blurred1.jpg
pegasus/theme/browser/images/blurred4.jpg
pegasus/theme/browser/images/blurred45.jpg
pegasus/theme/browser/images/blurred5.jpg
pegasus/theme/browser/images/calendar.png
pegasus/theme/browser/images/crumbs.png
pegasus/theme/browser/images/fond_off.png
pegasus/theme/browser/images/fond_off2.png
pegasus/theme/browser/images/fond_off3.png
pegasus/theme/browser/images/logo_uns.png
pegasus/theme/browser/images/pb_close.png
pegasus/theme/browser/images/portal-header.png
pegasus/theme/browser/images/snow.png
pegasus/theme/browser/images/snow2.png
pegasus/theme/browser/images/snow3.png
pegasus/theme/browser/images/tag_mask.png
pegasus/theme/browser/images/tag_mask_overlay.png
pegasus/theme/browser/images/time.png
pegasus/theme/browser/images/country-flags/cn.gif
pegasus/theme/browser/images/country-flags/fr.gif
pegasus/theme/browser/images/country-flags/gb.gif
pegasus/theme/browser/images/country-flags/it.gif
pegasus/theme/browser/images/fonts/IcoMoon.eot
pegasus/theme/browser/images/fonts/IcoMoon.svg
pegasus/theme/browser/images/fonts/IcoMoon.ttf
pegasus/theme/browser/images/fonts/IcoMoon.woff
pegasus/theme/browser/images/fonts/hero-webfont.eot
pegasus/theme/browser/images/fonts/hero-webfont.svg
pegasus/theme/browser/images/fonts/hero-webfont.ttf
pegasus/theme/browser/images/fonts/hero-webfont.woff
