Metadata-Version: 1.1
Name: pegasus.theme
Version: 1.3
Summary: An installable theme for Plone 3
Home-page: http://svn.plone.org/svn/collective/
Author: Jerome Navarro (Universite Nice Sophia Antipolis UNS), Bordonado Christophe (UNS)
Author-email: tice@unice.fr
License: CECILL
Platform: UNKNOWN
Classifier: Framework :: Plone
Classifier: Programming Language :: Python
